[{"title":"Prueba","description":"Descripcion prueba","price":200,"thumbnail":"N/A","stock":15,"code":"uuF3k9","id":1},{"title":"Prueba","description":"Descripcion prueba","price":200,"thumbnail":"N/A","stock":15,"code":"uuF3k9","id":2},{"title":"Prueba","description":"Descripcion prueba","price":200,"thumbnail":"N/A","stock":15,"code":"uuF3k9","id":3},{"title":"Prueba","description":"Descripcion prueba","price":200,"thumbnail":"N/A","stock":15,"code":"uuF3k9","id":4},{"title":"Prueba","description":"Descripcion prueba","price":200,"thumbnail":"N/A","stock":15,"code":"uuF3k9","id":6},{"title":"Prueba","description":"Descripcion prueba","price":200,"thumbnail":"N/A","stock":15,"code":"uuF3k9","id":7},{"title":"Prueba","description":"Descripcion prueba","price":200,"thumbnail":"N/A","stock":15,"code":"uuF3k9","id":8},{"title":"Prueba","description":"Descripcion prueba","price":200,"thumbnail":"N/A","stock":15,"code":"uuF3k9","id":9},{"title":"Prueba","description":"Descripcion prueba","price":200,"thumbnail":"N/A","stock":15,"code":"uuF3k9","id":10},{"title":"Prueba","description":"Descripcion prueba","price":200,"thumbnail":"N/A","stock":15,"code":"uuF3k9","id":11},{"title":"Prueba","description":"Descripcion prueba","price":200,"thumbnail":"N/A","stock":15,"code":"uuF3k9","id":12},{"title":"Prueba","description":"Descripcion prueba","price":200,"thumbnail":"N/A","stock":15,"code":"uuF3k9","id":13},{"title":"Prueba","description":"Descripcion prueba","price":200,"thumbnail":"N/A","stock":15,"code":"uuF3k9","id":14},{"title":"Prueba","description":"Descripcion prueba","price":200,"thumbnail":"N/A","stock":15,"code":"uuF3k9","id":15},{"title":"Prueba","description":"Descripcion prueba","price":200,"thumbnail":"N/A","stock":15,"code":"uuF3k9","id":16},{"title":"Prueba","description":"Descripcion prueba","price":200,"thumbnail":"N/A","stock":15,"code":"uuF3k9","id":17},{"title":"Prueba","description":"Descripcion prueba","price":200,"thumbnail":"N/A","stock":15,"code":"uuF3k9","id":18},{"title":"Prueba","description":"Descripcion prueba","price":200,"thumbnail":"N/A","stock":15,"code":"uuF3k9","id":19},{"title":"Prueba","description":"Descripcion prueba","price":200,"thumbnail":"N/A","stock":15,"code":"uuF3k9","id":20},{"title":"Prueba","description":"Descripcion prueba","price":200,"thumbnail":"N/A","stock":15,"code":"uuF3k9","id":21},{"title":"Prueba","description":"Descripcion prueba","price":200,"thumbnail":"N/A","stock":15,"code":"uuF3k9","id":22},{"title":"Prueba","description":"Descripcion prueba","price":200,"thumbnail":"N/A","stock":15,"code":"uuF3k9","id":23},{"id":24,"status":true},{"id":25,"status":true},{"id":26,"title":"Prueba","description":"Descripcion prueba","price":200,"thumbnail":"N/A","code":"uuF3k9","stock":15,"status":true,"category":"telefono"},{"id":27,"title":"Prueba","description":"Descripcion prueba","price":200,"thumbnail":"N/A","code":"uuF3k9","stock":15,"status":true,"category":"telefono"},{"id":28,"title":"Prueba","description":"Descripcion prueba","price":200,"thumbnail":"N/A","code":"uuF3k9","stock":15,"status":true,"category":"telefono"}]